{"EupgFOKNOGyyE3fHj6gpNQ==":"pocket-llama-studios-logo.png","BbNOa+F1REc/20TIEzx4Ug==":"splash-image.png","80OTSRqow773DAT9ro6EEQ==":"toasty-logo-shadow.png","p25O+H2CmnWe3EmqWyWlow==":"tessa01.png","1VumBkNzHhw+WlUpcuaIQQ==":"adam.gif","Oob9Kh+bu1jnOA4YdB9BKA==":"bag.gif","Fmr7k/m37WFc6rvOVjqwFQ==":"cave.gif","mPLESpNP+rBXTvKIhIqR9w==":"shop.gif","dCFHeInY5xL70e7l8Edsiw==":"factory.gif","7y4D5gauVv7+VkxOYMNhPA==":"dialogue.gif","dy5mnIof4z7jYvE2Nqo4QA==":"combat.gif","Xmtq5lQc/jxrQnkdtckY6Q==":"croakus.gif","aj3UUiXaQioPy29Ga8JzYA==":"wilhelm-kickstarer-v2.gif","vPU6GUmker0CUnaklLcvzA==":"tessa01-1.png","eSK2/coB/yWqu0HBbUws/g==":"404moonmen.jpg","SP2sBWv7bcPWTWOCqBFQDA==":"bag2.gif","m6OD5vhXRbr5ZkIwvmhwHw==":"ash01.png","CSvluXO+wdhxm8Z/mfa4Ew==":"doops-grin-2.png","sPGDs2LnuArRO0+YQ3BDGw==":"drawing-beard.png","QhuJJwkkssqcmwSb8HPqAA==":"doops-grin-3.png","yBsrkMELqf2yV8b57N13qQ==":"drawing-beard-1.png","XWL9bnXb8wHlJqmDhOthIA==":"story.png","gnSdmErbDHlK/xFG5F4UyA==":"wilhelm-back.jpg","OnQmN3Vj2oS51qgMmq46hw==":"2020-03-05-21-34-44-matt-bug.aseprite-aseprite-v1.2.16.3-x64.png"}